csv_postgres_loader/__init__.py
csv_postgres_loader/database.py
csv_postgres_loader/loader.py
csv_postgres_loader/py.typed
csv_postgres_loader/server.py
csv_postgres_loader/validator.py
csv_postgres_loader-0.1.0.dist-info/WHEEL
csv_postgres_loader-0.1.0.dist-info/entry_points.txt
csv_postgres_loader-0.1.0.dist-info/METADATA
csv_postgres_loader-0.1.0.dist-info/RECORD
