Metadata-Version: 2.3
Name: csv-postgres-loader
Version: 0.1.0
Summary: MCP server to load CSV files to PostgreSQL with validation and progress tracking
Keywords: mcp,csv,postgresql,database,loader,model-context-protocol
Author: Ravi Ramadoss
Author-email: Ravi Ramadoss <ravi.ramadoss@protonmail.com>
License: MIT
Classifier: Development Status :: 4 - Beta
Classifier: Intended Audience :: Developers
Classifier: License :: OSI Approved :: MIT License
Classifier: Programming Language :: Python :: 3
Classifier: Programming Language :: Python :: 3.10
Classifier: Programming Language :: Python :: 3.11
Classifier: Programming Language :: Python :: 3.12
Classifier: Programming Language :: Python :: 3.13
Classifier: Topic :: Database
Classifier: Topic :: Software Development :: Libraries :: Python Modules
Requires-Dist: mcp>=1.0.0
Requires-Dist: psycopg2-binary>=2.9.9
Requires-Dist: tqdm>=4.66.0
Requires-Dist: pytest>=8.0.0 ; extra == 'dev'
Requires-Dist: pytest-cov>=4.1.0 ; extra == 'dev'
Requires-Dist: pytest-asyncio>=0.23.0 ; extra == 'dev'
Requires-Dist: pre-commit>=3.5.0 ; extra == 'dev'
Requires-Python: >=3.10
Project-URL: Homepage, https://github.com/raviramadoss/mcp-csv-postgres
Project-URL: Issues, https://github.com/raviramadoss/mcp-csv-postgres/issues
Project-URL: Repository, https://github.com/raviramadoss/mcp-csv-postgres
Provides-Extra: dev
